pycarnot/__init__.py
pycarnot/const.py
pycarnot/exceptions.py
pycarnot-0.1.0.dist-info/LICENSE
pycarnot-0.1.0.dist-info/METADATA
pycarnot-0.1.0.dist-info/WHEEL
pycarnot-0.1.0.dist-info/RECORD
